LICENSE.txt
MANIFEST.in
README.rst
setup.cfg
setup.py
nzmetservice/__init__.py
nzmetservice/ftp_transfer.py
nzmetservice/process.py
nzmetservice/util.py
nzmetservice.egg-info/PKG-INFO
nzmetservice.egg-info/SOURCES.txt
nzmetservice.egg-info/dependency_links.txt
nzmetservice.egg-info/requires.txt
nzmetservice.egg-info/top_level.txt
nzmetservice/datasets/__init__.py
nzmetservice/datasets/wrf_hourly_precip_nz8km_test.nc
nzmetservice/tests/__init__.py
nzmetservice/tests/test_process.py