Metadata-Version: 1.1
Name: nzmetservice
Version: 1.0.3
Summary: functions to download and process metservice data
Home-page: https://github.com/mullenkamp/nzmetservice
Author: Mike Kittridge
Author-email: mullenkamp1@gmail.com
License: UNKNOWN
Keywords: rainfall forecast
Platform: UNKNOWN
Classifier: Development Status :: 3 - Alpha
Classifier: Intended Audience :: Developers
Classifier: Topic :: Software Development :: Build Tools
Classifier: License :: OSI Approved :: Apache Software License
Classifier: Programming Language :: Python :: 2
Classifier: Programming Language :: Python :: 2.7
Classifier: Programming Language :: Python :: 3
Classifier: Programming Language :: Python :: 3.4
Classifier: Programming Language :: Python :: 3.5
Classifier: Programming Language :: Python :: 3.6
